Metadata-Version: 2.1
Name: stasis-ssg
Version: 0.1.3
Summary: A simple static site generator with deployment to S3/Cloudfront
Home-page: https://github.com/czep/stasis
Author: Scott Czepiel
Author-email: dev@czep.net
License: UNKNOWN
Keywords: static site generator,web development,blog
Platform: UNKNOWN
Classifier: Development Status :: 3 - Alpha
Classifier: Intended Audience :: Developers
Classifier: Topic :: Software Development :: Build Tools
Classifier: Topic :: Text Processing :: Markup :: Markdown
Classifier: License :: OSI Approved :: MIT License
Classifier: Programming Language :: Python :: 3
Classifier: Programming Language :: Python :: 3.9
Classifier: Programming Language :: Python :: 3 :: Only
Requires-Python: >=3.9, <4
Requires-Dist: jinja2
Requires-Dist: boto3
Requires-Dist: python-frontmatter
